[
  {
    "ContainingType": "TPTicketingPS.API.Controllers.V1.EventsController",
    "Method": "GetEvents",
    "RelativePath": "api/v1/events",
    "HttpMethod": "GET",
    "IsController": true,
    "Order": 0,
    "Parameters": [],
    "ReturnTypes": [
      {
        "Type": "System.Void",
        "MediaTypes": [],
        "StatusCode": 200
      }
    ]
  },
  {
    "ContainingType": "TPTicketingPS.API.Controllers.V1.ReservationsController",
    "Method": "Create",
    "RelativePath": "api/v1/reservations",
    "HttpMethod": "POST",
    "IsController": true,
    "Order": 0,
    "Parameters": [
      {
        "Name": "request",
        "Type": "TPTicketingPS.Application.Reservations.UseCases.CreateReservation.CreateReservationRequest",
        "IsRequired": true
      }
    ],
    "ReturnTypes": [
      {
        "Type": "TPTicketingPS.Application.Reservations.Dtos.ReservationDto",
        "MediaTypes": [
          "application/json"
        ],
        "StatusCode": 201
      },
      {
        "Type": "Microsoft.AspNetCore.Mvc.ProblemDetails",
        "MediaTypes": [
          "application/json"
        ],
        "StatusCode": 400
      },
      {
        "Type": "Microsoft.AspNetCore.Mvc.ProblemDetails",
        "MediaTypes": [
          "application/json"
        ],
        "StatusCode": 404
      },
      {
        "Type": "Microsoft.AspNetCore.Mvc.ProblemDetails",
        "MediaTypes": [
          "application/json"
        ],
        "StatusCode": 409
      }
    ]
  },
  {
    "ContainingType": "TPTicketingPS.API.Controllers.V1.ReservationsController",
    "Method": "GetById",
    "RelativePath": "api/v1/reservations/{reservationId}",
    "HttpMethod": "GET",
    "IsController": true,
    "Order": 0,
    "Parameters": [
      {
        "Name": "reservationId",
        "Type": "System.Guid",
        "IsRequired": true
      }
    ],
    "ReturnTypes": [
      {
        "Type": "TPTicketingPS.Application.Reservations.Dtos.ReservationDto",
        "MediaTypes": [
          "application/json"
        ],
        "StatusCode": 200
      },
      {
        "Type": "Microsoft.AspNetCore.Mvc.ProblemDetails",
        "MediaTypes": [
          "application/json"
        ],
        "StatusCode": 404
      }
    ],
    "EndpointName": "GetReservationById"
  },
  {
    "ContainingType": "TPTicketingPS.API.Controllers.V1.UsersController",
    "Method": "Create",
    "RelativePath": "api/v1/users",
    "HttpMethod": "POST",
    "IsController": true,
    "Order": 0,
    "Parameters": [
      {
        "Name": "request",
        "Type": "TPTicketingPS.Application.Users.UseCases.CreateUser.CreateUserRequest",
        "IsRequired": true
      }
    ],
    "ReturnTypes": [
      {
        "Type": "TPTicketingPS.Application.Users.Dtos.UserDto",
        "MediaTypes": [
          "application/json"
        ],
        "StatusCode": 201
      },
      {
        "Type": "Microsoft.AspNetCore.Mvc.ProblemDetails",
        "MediaTypes": [
          "application/json"
        ],
        "StatusCode": 400
      },
      {
        "Type": "Microsoft.AspNetCore.Mvc.ProblemDetails",
        "MediaTypes": [
          "application/json"
        ],
        "StatusCode": 409
      }
    ]
  },
  {
    "ContainingType": "TPTicketingPS.API.Controllers.V1.UsersController",
    "Method": "GetById",
    "RelativePath": "api/v1/users/{userId}",
    "HttpMethod": "GET",
    "IsController": true,
    "Order": 0,
    "Parameters": [
      {
        "Name": "userId",
        "Type": "System.Int32",
        "IsRequired": true
      }
    ],
    "ReturnTypes": [
      {
        "Type": "TPTicketingPS.Application.Users.Dtos.UserDto",
        "MediaTypes": [
          "application/json"
        ],
        "StatusCode": 200
      },
      {
        "Type": "Microsoft.AspNetCore.Mvc.ProblemDetails",
        "MediaTypes": [
          "application/json"
        ],
        "StatusCode": 404
      }
    ],
    "EndpointName": "GetUserById"
  },
  {
    "ContainingType": "TPTicketingPS.API.Controllers.V1.UsersController",
    "Method": "GetReservations",
    "RelativePath": "api/v1/users/{userId}/reservations",
    "HttpMethod": "GET",
    "IsController": true,
    "Order": 0,
    "Parameters": [
      {
        "Name": "userId",
        "Type": "System.Int32",
        "IsRequired": true
      },
      {
        "Name": "Status",
        "Type": "System.String",
        "IsRequired": false
      }
    ],
    "ReturnTypes": [
      {
        "Type": "System.Collections.Generic.IReadOnlyCollection\u00601[[TPTicketingPS.Application.Reservations.Dtos.ReservationDto, TPTicketingPS.Application, Version=1.0.0.0, Culture=neutral, PublicKeyToken=null]]",
        "MediaTypes": [
          "application/json"
        ],
        "StatusCode": 200
      },
      {
        "Type": "Microsoft.AspNetCore.Mvc.ProblemDetails",
        "MediaTypes": [
          "application/json"
        ],
        "StatusCode": 400
      },
      {
        "Type": "Microsoft.AspNetCore.Mvc.ProblemDetails",
        "MediaTypes": [
          "application/json"
        ],
        "StatusCode": 404
      }
    ]
  }
]